{
    "Right Alt (while pressed)": "grp:switch",
    "Left Alt (while pressed)": "grp:lswitch",
    "Left Win (while pressed)": "grp:lwin_switch",
    "Right Win (while pressed)": "grp:rwin_switch",
    "Any Win (while pressed)": "grp:win_switch",
    "Menu (while pressed), Shift+Menu for Menu": "grp:menu_switch",
    "Right Ctrl (while pressed)": "grp:rctrl_switch",
    "Right Alt": "grp:toggle",
    "Left Alt": "grp:lalt_toggle",
    "Caps Lock": "grp:caps_toggle",
    "Shift+Caps Lock": "grp:shift_caps_toggle",
    "Alt+Caps Lock": "grp:alt_caps_toggle",
    "Both Shift together": "grp:shifts_toggle",
    "Both Alt together": "grp:alts_toggle",
    "Both Ctrl together": "grp:ctrls_toggle",
    "Ctrl+Shift": "grp:ctrl_shift_toggle",
    "Left Ctrl+Left Shift": "grp:lctrl_lshift_toggle",
    "Right Ctrl+Right Shift": "grp:rctrl_rshift_toggle",
    "Alt+Ctrl": "grp:ctrl_alt_toggle",
    "Alt+Shift": "grp:alt_shift_toggle",
    "Left Alt+Left Shift": "grp:lalt_lshift_toggle",
    "Alt+Space": "grp:alt_space_toggle",
    "Menu": "grp:menu_toggle",
    "Left Win": "grp:lwin_toggle",
    "Win+Space": "grp:win_space_toggle",
    "Right Win": "grp:rwin_toggle",
    "Left Shift": "grp:lshift_toggle",
    "Right Shift": "grp:rshift_toggle",
    "Left Ctrl": "grp:lctrl_toggle",
    "Right Ctrl": "grp:rctrl_toggle",
    "Scroll Lock": "grp:sclk_toggle",
    "Left Ctrl+Left Win": "grp:lctrl_lwin_toggle"
}
