{
    "English (US)": [
        {
            "None": "",
            "Cherokee": "chr",
            "Hawaiian": "haw",
            "English (US, euro on 5)": "euro",
            "English (US, intl., with dead keys)": "intl",
            "English (US, alt. intl.)": "alt-intl",
            "English (Colemak)": "colemak",
            "English (Colemak-DH)": "colemak_dh",
            "English (Colemak-DH ISO)": "colemak_dh_iso",
            "English (Dvorak)": "dvorak",
            "English (Dvorak, intl., with dead keys)": "dvorak-intl",
            "English (Dvorak, alt. intl.)": "dvorak-alt-intl",
            "English (Dvorak, left-handed)": "dvorak-l",
            "English (Dvorak, right-handed)": "dvorak-r",
            "English (classic Dvorak)": "dvorak-classic",
            "English (programmer Dvorak)": "dvp",
            "English (Dvorak, Macintosh)": "dvorak-mac",
            "English (US, Symbolic)": "symbolic",
            "Russian (US, phonetic)": "rus",
            "English (Macintosh)": "mac",
            "English (intl., with AltGr dead keys)": "altgr-intl",
            "English (the divide/multiply toggle the layout)": "olpc2",
            "Serbo-Croatian (US)": "hbs",
            "English (Norman)": "norman",
            "English (Workman)": "workman",
            "English (Workman, intl., with dead keys)": "workman-intl"
        }
    ],
    "Afghanistan": [
        {
            "None": "",
            "Pashto": "ps",
            "Uzbek (Afghanistan)": "uz",
            "Pashto (Afghanistan, OLPC)": "ps-olpc",
            "Dari (Afghanistan, OLPC)": "fa-olpc",
            "Uzbek (Afghanistan, OLPC)": "uz-olpc"
        }
    ],
    "Arabic": [
        {

            "None": "",
            "Arabic (AZERTY)": "azerty",
            "Arabic (AZERTY, Eastern Arabic numerals)": "azerty_digits",
            "Arabic (Eastern Arabic numerals)": "digits",
            "Arabic (QWERTY)": "qwerty",
            "Arabic (QWERTY, Eastern Arabic numerals)": "qwerty_digits",
            "Arabic (Buckwalter)": "buckwalter",
            "Arabic (OLPC)": "olpc",
            "Arabic (Macintosh)": "mac"
        }
    ],
    "Albanian": [
        {

            "None": "",
            "Albanian (Plisi)": "plisi",
            "Albanian (Veqilharxhi)": "veqilharxhi"
        }
    ],
    "Armenian": [
        {

            "None": "",
            "Armenian (phonetic)": "phonetic",
            "Armenian (alt. phonetic)": "phonetic-alt",
            "Armenian (eastern)": "eastern",
            "Armenian (western)": "western",
            "Armenian (alt. eastern)": "eastern-alt"
        }
    ],
    "German (Austria)": [
        {

            "None": "",
            "German (Austria, no dead keys)": "nodeadkeys",
            "German (Austria, Macintosh)": "mac"
        }
    ],
    "Azerbaijani": [
        {

            "None": "",
            "Azerbaijani (Cyrillic)": "cyrillic"
        }
    ],
    "Belarusian": [
        {

            "None": "",
            "Belarusian (legacy)": "legacy",
            "Belarusian (Latin)": "latin",
            "Russian (Belarus)": "ru",
            "Belarusian (intl.)": "intl"
        }
    ],
    "Belgian": [
        {

            "None": "",
            "Belgian (alt.)": "oss",
            "Belgian (Latin-9 only, alt.)": "oss_latin9",
            "Belgian (ISO, alt.)": "iso-alternate",
            "Belgian (no dead keys)": "nodeadkeys",
            "Belgian (Wang 724 AZERTY)": "wang"
        }
    ],
    "Bangla": [
        {

            "None": "",
            "Bangla (Probhat)": "probhat"
        }
    ],
    "India": [
        {

            "None": "",
            "Bangla (India)": "ben",
            "Bangla (India, Probhat)": "ben_probhat",
            "Bangla (India, Baishakhi)": "ben_baishakhi",
            "Bangla (India, Bornona)": "ben_bornona",
            "Bangla (India, Gitanjali)": "ben_gitanjali",
            "Bangla (India, Baishakhi InScript)": "ben_inscript",
            "Manipuri (Eeyek)": "eeyek",
            "Gujarati": "guj",
            "Punjabi (Gurmukhi)": "guru",
            "Punjabi (Gurmukhi Jhelum)": "jhelum",
            "Kannada": "kan",
            "Kannada (KaGaPa, phonetic)": "kan-kagapa",
            "Malayalam": "mal",
            "Malayalam (Lalitha)": "mal_lalitha",
            "Malayalam (enhanced InScript, with rupee)": "mal_enhanced",
            "Oriya": "ori",
            "Oriya (Bolnagri)": "ori-bolnagri",
            "Oriya (Wx)": "ori-wx",
            "Ol Chiki": "olck",
            "Tamil (TamilNet '99)": "tam_tamilnet",
            "Tamil (TamilNet '99 with Tamil numerals)": "tam_tamilnet_with_tam_nums",
            "Tamil (TamilNet '99, TAB encoding)": "tam_tamilnet_TAB",
            "Tamil (TamilNet '99, TSCII encoding)": "tam_tamilnet_TSCII",
            "Tamil (InScript)": "tam",
            "Telugu": "tel",
            "Telugu (KaGaPa, phonetic)": "tel-kagapa",
            "Telugu (Sarala)": "tel-sarala",
            "Urdu (phonetic)": "urd-phonetic",
            "Urdu (alt. phonetic)": "urd-phonetic3",
            "Urdu (Windows)": "urd-winkeys",
            "Hindi (Bolnagri)": "bolnagri",
            "Hindi (Wx)": "hin-wx",
            "Hindi (KaGaPa, phonetic)": "hin-kagapa",
            "Sanskrit (KaGaPa, phonetic)": "san-kagapa",
            "Marathi (KaGaPa, phonetic)": "mar-kagapa",
            "English (India, with rupee)": "eng",
            "Indic IPA": "iipa",
            "Marathi (enhanced InScript)": "marathi"
        }
    ],
    "Bosnian": [
        {

            "None": "",
            "Bosnian (with guillemets)": "alternatequotes",
            "Bosnian (with Bosnian digraphs)": "unicode",
            "Bosnian (US, with Bosnian digraphs)": "unicodeus",
            "Bosnian (US)": "us"
        }
    ],
    "Brazil": [
        {

            "None": "",
            "Portuguese (Brazil, no dead keys)": "nodeadkeys",
            "Portuguese (Brazil, Dvorak)": "dvorak",
            "Portuguese (Brazil, Nativo)": "nativo",
            "Portuguese (Brazil, Nativo for US keyboards)": "nativo-us",
            "Esperanto (Brazil, Nativo)": "nativo-epo",
            "Portuguese (Brazil, IBM/Lenovo ThinkPad)": "thinkpad"
        }
    ],
    "Bulgarian": [
        {
            "None": "",
            "Bulgarian (traditional phonetic)": "phonetic",
            "Bulgarian (new phonetic)": "bas_phonetic",
            "Bulgarian (enhanced)": "bekl"
        }
    ],
    "Berber (Algeria, Latin)": [
        {
            "None": "",
            "Kabyle (AZERTY, with dead keys)": "azerty-deadkeys",
            "Kabyle (QWERTY, UK, with dead keys)": "qwerty-gb-deadkeys",
            "Kabyle (QWERTY, US, with dead keys)": "qwerty-us-deadkeys",
            "Berber (Algeria, Tifinagh)": "ber",
            "Arabic (Algeria)": "ar"
        }
    ],
    "Arabic (Morocco)": [
        {
            "None": "",
            "French (Morocco)": "french",
            "Berber (Morocco, Tifinagh)": "tifinagh",
            "Berber (Morocco, Tifinagh alt.)": "tifinagh-alt",
            "Berber (Morocco, Tifinagh phonetic, alt.)": "tifinagh-alt-phonetic",
            "Berber (Morocco, Tifinagh extended)": "tifinagh-extended",
            "Berber (Morocco, Tifinagh phonetic)": "tifinagh-phonetic",
            "Berber (Morocco, Tifinagh extended phonetic)": "tifinagh-extended-phonetic",
            "Tarifit": "rif"
        }
    ],
    "English (Cameroon)": [
        {
            "None": "",
            "French (Cameroon)": "french",
            "Cameroon Multilingual (QWERTY, intl.)": "qwerty",
            "Cameroon (AZERTY, intl.)": "azerty",
            "Cameroon (Dvorak, intl.)": "dvorak",
            "Mmuock": "mmuock"
        }
    ],
    "Mon": [
        {
            "None": "",
            "Burmese Zawgyi": "zawgyi",
            "Shan": "shn",
            "Shan (Zawgyi Tai)": "zgt",
            "Mon": "mnw",
            "Mon (A1)": "mnw-a1"
        }
    ],
    "French (Canada)": [
        {
            "None": "",
            "French (Canada, Dvorak)": "fr-dvorak",
            "French (Canada, legacy)": "fr-legacy",
            "Canadian (intl.)": "multix",
            "Canadian (intl., 1st part)": "multi",
            "Canadian (intl., 2nd part)": "multi-2gr",
            "Inuktitut": "ike",
            "English (Canada)": "eng"
        }
    ],
    "Mongolian": [
        {
            "None": "",
            "Mongolian (Bichig)": "mon_trad",
            "Mongolian (Todo)": "mon_trad_todo",
            "Mongolian (Xibe)": "mon_trad_xibe",
            "Mongolian (Manchu)": "mon_trad_manchu",
            "Mongolian (Galik)": "mon_trad_galik",
            "Mongolian (Todo Galik)": "mon_todo_galik",
            "Mongolian (Manchu Galik)": "mon_manchu_galik",
            "Tibetan": "tib",
            "Tibetan (with ASCII numerals)": "tib_asciinum",
            "Uyghur": "ug",
            "Hanyu Pinyin Letters (with AltGr dead keys)": "altgr-pinyin"
        }
    ],
    "Croatian": [
        {
            "None": "",
            "Croatian (with guillemets)": "alternatequotes",
            "Croatian (with Croatian digraphs)": "unicode",
            "Croatian (US, with Croatian digraphs)": "unicodeus",
            "Croatian (US)": "us"
        }
    ],
    "Czech": [
        {
            "None": "",
            "Czech (with &lt;|&gt; key)": "bksl",
            "Czech (QWERTY)": "qwerty",
            "Czech (QWERTY, extended backslash)": "qwerty_bksl",
            "Czech (QWERTY, Macintosh)": "qwerty-mac",
            "Czech (UCW, only accented letters)": "ucw",
            "Czech (US, Dvorak, UCW support)": "dvorak-ucw",
            "Russian (Czech, phonetic)": "rus"
        }
    ],
    "Danish": [
        {
            "None": "",
            "Danish (no dead keys)": "nodeadkeys",
            "Danish (Windows)": "winkeys",
            "Danish (Macintosh)": "mac",
            "Danish (Macintosh, no dead keys)": "mac_nodeadkeys",
            "Danish (Dvorak)": "dvorak"
        }
    ],
    "Dutch": [
        {
            "None": "",
            "Dutch (US)": "us",
            "Dutch (Macintosh)": "mac",
            "Dutch (standard)": "std"
        }
    ],
    "Estonian": [
        {
            "None": "",
            "Estonian (no dead keys)": "nodeadkeys",
            "Estonian (Dvorak)": "dvorak",
            "Estonian (US)": "us"
        }
    ],
    "Iran": [
        {
            "None": "",
            "Persian (with Persian keypad)": "pes_keypad",
            "Kurdish (Iran, Latin Q)": "ku",
            "Kurdish (Iran, F)": "ku_f",
            "Kurdish (Iran, Latin Alt-Q)": "ku_alt",
            "Kurdish (Iran, Arabic-Latin)": "ku_ara"
        }
    ],
    "Iraqi": [
        {
            "None": "",
            "Kurdish (Iraq, Latin Q)": "ku",
            "Kurdish (Iraq, F)": "ku_f",
            "Kurdish (Iraq, Latin Alt-Q)": "ku_alt",
            "Kurdish (Iraq, Arabic-Latin)": "ku_ara"
        }
    ],
    "Faroese": [
        {
            "None": "",
            "Faroese (no dead keys)": "nodeadkeys"
        }
    ],
    "Finnish": [
        {
            "None": "",
            "Finnish (Windows)": "winkeys",
            "Finnish (classic)": "classic",
            "Finnish (classic, no dead keys)": "nodeadkeys",
            "Northern Saami (Finland)": "smi",
            "Finnish (Macintosh)": "mac"
        }
    ],
    "French": [
        {
            "None": "",
            "French (no dead keys)": "nodeadkeys",
            "French (alt.)": "oss",
            "French (alt., Latin-9 only)": "oss_latin9",
            "French (alt., no dead keys)": "oss_nodeadkeys",
            "French (legacy, alt.)": "latin9 ",
            "French (legacy, alt., no dead keys)": "latin9_nodeadkeys",
            "French (BEPO)": "bepo",
            "French (BEPO, Latin-9 only)": "bepo_latin9",
            "French (BEPO, AFNOR)": "bepo_afnor",
            "French (Dvorak)": "dvorak",
            "French (Macintosh)": "mac",
            "French (AZERTY)": "azerty",
            "French (AZERTY, AFNOR)": "afnor",
            "French (Breton)": "bre",
            "Occitan": "oci",
            "Georgian (France, AZERTY Tskapo)": "geo",
            "French (US)": "us"
        }
    ],
    "English (Ghana)": [
        {
            "None": "",
            "English (Ghana, multilingual)": "generic",
            "Akan": "akan",
            "Ewe": "ewe",
            "Fula": "fula",
            "Ga": "ga",
            "Hausa (Ghana)": "hausa",
            "Avatime": "avn",
            "English (Ghana, GILLBT)": "gillbt"
        }
    ],
    "Georgian": [
        {
            "None": "",
            "Georgian (ergonomic)": "ergonomic",
            "Georgian (MESS)": "mess",
            "Russian (Georgia)": "ru",
            "Ossetian (Georgia)": "os"
        }
    ],
    "German": [
        {
            "None": "",
            "German (dead acute)": "deadacute",
            "German (dead grave acute)": "deadgraveacute",
            "German (no dead keys)": "nodeadkeys",
            "German (E1)": "e1",
            "German (E2)": "e2",
            "German (T3)": "T3",
            "German (US)": "us",
            "Romanian (Germany)": "ro",
            "Romanian (Germany, no dead keys)": "ro_nodeadkeys",
            "German (Dvorak)": "dvorak",
            "German (Neo 2)": "neo",
            "German (Macintosh)": "mac",
            "German (Macintosh, no dead keys)": "mac_nodeadkeys",
            "Lower Sorbian": "dsb",
            "Lower Sorbian (QWERTZ)": "dsb_qwertz",
            "German (QWERTY)": "qwerty",
            "Turkish (Germany)": "tr",
            "Russian (Germany, phonetic)": "ru",
            "German (dead tilde)": "deadtilde"
        }
    ],
    "Greek": [
        {
            "None": "",
            "Greek (simple)": "simple",
            "Greek (extended)": "extended",
            "Greek (no dead keys)": "Greek (no dead keys)",
            "Greek (polytonic)": "polytonic"
        }
    ],
    "Hungarian": [
        {
            "None": "",
            "Hungarian (standard)": "standard",
            "Hungarian (no dead keys)": "nodeadkeys",
            "Hungarian (QWERTY)": "qwerty"
        }
    ],
    "Icelandic": [
        {
            "None": "",
            "Icelandic (Macintosh, legacy)": "mac_legacy",
            "Icelandic (Macintosh)": "mac",
            "Icelandic (Dvorak)": "dvorak"
        }
    ],
    "Hebrew": [
        {
            "None": "",
            "Hebrew (lyx)": "lyx",
            "Hebrew (phonetic)": "phonetic",
            "Hebrew (Biblical, Tiro)": "biblical"
        }
    ],
    "Italian": [
        {
            "None": "",
            "Italian (no dead keys)": "nodeadkeys",
            "Italian (Windows)": "winkeys",
            "Italian (Macintosh)": "mac",
            "Italian (US)": "us",
            "Georgian (Italy)": "geo",
            "Italian (IBM 142)": "ibm",
            "Italian (intl., with dead keys)": "intl",
            "Sicilian": "scn",
            "Friulian (Italy)": "fur"
        }
    ],
    "Japanese": [
        {
            "None": "",
            "Japanese (Kana)": "kana",
            "Japanese (Kana 86)": "kana86",
            "Japanese (OADG 109A)": "OADG109A",
            "Japanese (Macintosh)": "mac",
            "Japanese (Dvorak)": "dvorak"
        }
    ],
    "Kyrgyz": [
        {
            "None": "",
            "Kyrgyz (phonetic)": "phonetic"
        }
    ],
    "Kazakh": [
        {
            "None": "",
            "Russian (Kazakhstan, with Kazakh)": "ruskaz",
            "Kazakh (with Russian)": "kazrus",
            "Kazakh (extended)": "ext",
            "Kazakh (Latin)": "latin"
        }
    ],
    "Lao": [
        {
            "None": "",
            "Lao (STEA)": "stea"
        }
    ],
    "Spanish (Latin American)": [
        {
            "None": "",
            "Spanish (Latin American, no dead keys)": "nodeadkeys",
            "Spanish (Latin American, dead tilde)": "deadtilde",
            "Spanish (Latin American, Dvorak)": "dvorak",
            "Spanish (Latin American, Colemak)": "colemak",
            "Spanish (Latin American, Colemak for gaming)": "colemak-gaming"
        }
    ],
    "Lithuanian": [
        {
            "None": "",
            "Lithuanian (standard)": "std",
            "Lithuanian (US)": "us",
            "Lithuanian (IBM LST 1205-92)": "ibm",
            "Lithuanian (LEKP)": "lekp",
            "Lithuanian (LEKPa)": "lekpa",
            "Samogitian": "sgs",
            "Lithuanian (Ratise)": "ratise"
        }
    ],
    "Latvian": [
        {
            "None": "",
            "Latvian (apostrophe)": "apostrophe",
            "Latvian (tilde)": "tilde",
            "Latvian (F)": "fkey",
            "Latvian (modern)": "modern",
            "Latvian (ergonomic, ŪGJRMV)": "ergonomic",
            "Latvian (adapted)": "adapted"
        }
    ],
    "Montenegrin": [
        {
            "None": "",
            "Montenegrin (Cyrillic)": "cyrillic",
            "Montenegrin (Cyrillic, ZE and ZHE swapped)": "cyrillicyz",
            "Montenegrin (Latin, Unicode)": "latinunicode",
            "Montenegrin (Latin, QWERTY)": "latinyz",
            "Montenegrin (Latin, Unicode, QWERTY)": "latinunicodeyz",
            "Montenegrin (Cyrillic, with guillemets)": "cyrillicalternatequotes",
            "Montenegrin (Latin, with guillemets)": "latinalternatequotes"
        }
    ],
    "Macedonian": [
        {
            "None": "",
            "Macedonian (no dead keys)": "nodeadkeys"
        }
    ],
    "Maltese": [
        {
            "None": "",
            "Maltese (US)": "us",
            "Maltese (US, with AltGr overrides)": "alt-us",
            "Maltese (UK, with AltGr overrides)": "alt-gb"
        }
    ],
    "Norwegian": [
        {
            "None": "",
            "Norwegian (no dead keys)": "nodeadkeys",
            "Norwegian (Windows)": "winkeys",
            "Norwegian (Dvorak)": "dvorak",
            "Northern Saami (Norway)": "smi",
            "Northern Saami (Norway, no dead keys)": "smi_nodeadkeys",
            "Norwegian (Macintosh)": "mac",
            "Norwegian (Macintosh, no dead keys)": "mac_nodeadkeys",
            "Norwegian (Colemak)": "colemak"
        }
    ],
    "Polish": [
        {
            "None": "",
            "Polish (legacy)": "legacy",
            "Polish (QWERTZ)": "qwertz",
            "Polish (Dvorak)": "dvorak",
            "Polish (Dvorak, with Polish quotes on quotemark key)": "dvorak_quotes",
            "Polish (Dvorak, with Polish quotes on key 1)": "dvorak_altquotes",
            "Kashubian": "csb",
            "Silesian": "szl",
            "Russian (Poland, phonetic Dvorak)": "ru_phonetic_dvorak",
            "Polish (programmer Dvorak)": "dvp"
        }
    ],
    "Portuguese": [
        {
            "None": "",
            "Portuguese (no dead keys)": "nodeadkeys",
            "Portuguese (Macintosh)": "mac",
            "Portuguese (Macintosh, no dead keys)": "mac_nodeadkeys",
            "Portuguese (Nativo)": "nativo",
            "Portuguese (Nativo for US keyboards)": "nativo-us",
            "Esperanto (Portugal, Nativo)": "nativo-epo"
        }
    ],
    "Romanian": [
        {
            "None": "",
            "Romanian (standard)": "std",
            "Romanian (Windows)": "winkeys"
        }
    ],
    "Russian": [
        {
            "None": "",
            "Russian (phonetic)": "ru",
            "Russian (phonetic, Windows)": "phonetic_winkeys",
            "Russian (phonetic, YAZHERTY)": "phonetic_YAZHERTY",
            "Russian (typewriter)": "typewriter",
            "Russian (legacy)": "legacy",
            "Russian (typewriter, legacy)": "typewriter-legacy",
            "Tatar": "tt",
            "Ossetian (legacy)": "os_legacy",
            "Ossetian (Windows)": "os_winkeys",
            "Chuvash": "cv",
            "Chuvash (Latin)": "cv_latin",
            "Udmurt": "udm",
            "Komi": "kom",
            "Yakut": "sah",
            "Kalmyk": "xal",
            "Russian (DOS)": "dos",
            "Russian (Macintosh)": "mac",
            "Serbian (Russia)": "srp",
            "Bashkirian": "bak",
            "Mari": "chm",
            "Russian (phonetic, AZERTY)": "phonetic_azerty",
            "Russian (phonetic, Dvorak)": "phonetic_dvorak",
            "Russian (phonetic, French)": "phonetic_fr"
        }
    ],
    "Serbian": [
        {
            "None": "",
            "Serbian (Cyrillic, ZE and ZHE swapped)": "yz",
            "Serbian (Latin)": "latin",
            "Serbian (Latin, Unicode)": "Serbian (Latin, Unicode)",
            "Serbian (Latin, QWERTY)": "latinyz",
            "Serbian (Latin, Unicode, QWERTY)": "latinunicodeyz",
            "Serbian (Cyrillic, with guillemets)": "alternatequotes",
            "Serbian (Latin, with guillemets)": "latinalternatequotes",
            "Pannonian Rusyn": "rue"
        }
    ],
    "Slovenian": [
        {
            "None": "",
            "Slovenian (with guillemets)": "alternatequotes",
            "Slovenian (US)": "us"
        }
    ],
    "Slovak": [
        {
            "None": "",
            "Slovak (extended backslash)": "bksl",
            "Slovak (QWERTY)": "qwerty",
            "Slovak (QWERTY, extended backslash)": "qwerty_bksl"
        }
    ],
    "Spanish": [
        {
            "None": "",
            "Spanish (no dead keys)": "nodeadkeys",
            "Spanish (Windows)": "winkeys",
            "Spanish (dead tilde)": "deadtilde",
            "Spanish (Dvorak)": "dvorak",
            "Asturian (Spain, with bottom-dot H and L)": "ast",
            "Catalan (Spain, with middle-dot L)": "cat",
            "Spanish (Macintosh)": "mac"
        }
    ],
    "Swedish": [
        {
            "None": "",
            "Swedish (no dead keys)": "nodeadkeys",
            "Swedish (Dvorak)": "dvorak",
            "Russian (Sweden, phonetic)": "rus",
            "Russian (Sweden, phonetic, no dead keys)": "rus_nodeadkeys",
            "Northern Saami (Sweden)": "smi",
            "Swedish (Macintosh)": "mac",
            "Swedish (Svdvorak)": "svdvorak",
            "Swedish (Dvorak, intl.)": "us_dvorak",
            "Swedish (US)": "us",
            "Swedish Sign Language": "swl"
        }
    ],
    "German (Switzerland)": [
        {
            "None": "",
            "German (Switzerland, legacy)": "legacy",
            "German (Switzerland, no dead keys)": "de_nodeadkeys",
            "French (Switzerland)": "fr",
            "French (Switzerland, no dead keys)": "fr_nodeadkeys",
            "French (Switzerland, Macintosh)": "fr_mac",
            "German (Switzerland, Macintosh)": "de_mac"
        }
    ],
    "Arabic (Syria)": [
        {
            "None": "",
            "Syriac": "syc",
            "Syriac (phonetic)": "syc_phonetic",
            "Kurdish (Syria, Latin Q)": "ku",
            "Kurdish (Syria, F)": "ku_f",
            "Kurdish (Syria, Latin Alt-Q)": "ku_alt"
        }
    ],
    "Tajik": [
        {
            "None": "",
            "Tajik (legacy)": "legacy"
        }
    ],
    "Sri Lanka": [
        {
            "None": "",
            "Tamil (Sri Lanka, TamilNet '99)": "tam_unicode",
            "Tamil (Sri Lanka, TamilNet '99, TAB encoding)": "tam_TAB",
            "Sinhala (US)": "us"
        }
    ],
    "Thai": [
        {
            "None": "",
            "Thai (TIS-820.2538)": "tis",
            "Thai (Pattachote)": "pat"
        }
    ],
    "Turkish": [
        {
            "None": "",
            "Turkish (F)": "f",
            "Turkish (Alt-Q)": "alt",
            "Kurdish (Turkey, Latin Q)": "ku",
            "Kurdish (Turkey, F)": "ku_f",
            "Kurdish (Turkey, Latin Alt-Q)": "ku_alt",
            "Turkish (intl., with dead keys)": "intl",
            "Ottoman (Q)": "ot",
            "Ottoman (F)": "otf",
            "Old Turkic": "otk",
            "Old Turkic (F)": "otkf"
        }
    ],
    "Taiwanese": [
        {
            "None": "",
            "Taiwanese (indigenous)": "indigenous",
            "Saisiyat (Taiwan)": "saisiyat"
        }
    ],
    "Ukrainian": [
        {
            "None": "",
            "Ukrainian (phonetic)": "phonetic",
            "Ukrainian (typewriter)": "typewriter",
            "Ukrainian (Windows)": "winkeys",
            "Ukrainian (macOS)": "macOS",
            "Ukrainian (legacy)": "legacy",
            "Ukrainian (standard RSTU)": "rstu",
            "Russian (Ukraine, standard RSTU)": "rstu_ru",
            "Ukrainian (homophonic)": "homophonic",
            "Crimean Tatar (Turkish Q)": "crh",
            "Crimean Tatar (Turkish F)": "crh_f",
            "Crimean Tatar (Turkish Alt-Q)": "crh_alt"
        }
    ],
    "English (UK)": [
        {
            "None": "",
            "English (UK, extended, Windows)": "extd",
            "English (UK, intl., with dead keys)": "intl",
            "English (UK, Dvorak)": "dvorak",
            "English (UK, Dvorak, with UK punctuation)": "dvorakukp",
            "English (UK, Macintosh)": "mac",
            "English (UK, Macintosh, intl.)": "mac_intl",
            "English (UK, Colemak)": "colemak",
            "English (UK, Colemak-DH)": "colemak_dh",
            "Polish (British keyboard)": "pl",
            "Scottish Gaelic": "gla"
        }
    ],
    "Uzbek": [
        {
            "None": "",
            "Uzbek (Latin)": "latin"
        }
    ],
    "Vietnamese": [
        {
            "None": "",
            "Vietnamese (US)": "us",
            "Vietnamese (French)": "fr"
        }
    ],
    "Korean": [
        {
            "None": "",
            "Korean (101/104-key compatible)": "kr104"
        }
    ],
    "Irish": [
        {
            "None": "",
            "CloGaelach": "CloGaelach",
            "Irish (UnicodeExpert)": "UnicodeExpert",
            "Ogham": "ogam",
            "Ogham (IS434)": "ogam_is434"
        }
    ],
    "Urdu (Pakistan)": [
        {
            "None": "",
            "Urdu (Pakistan, CRULP)": "urd-crulp",
            "Urdu (Pakistan, NLA)": "urd-nla",
            "Arabic (Pakistan)": "ara",
            "Sindhi": "snd"
        }
    ],
    "Esperanto": [
        {
            "None": "",
            "Esperanto (legacy)": "legacy"
        }
    ],
    "English (Nigeria)": [
        {
            "None": "",
            "Igbo": "igbo",
            "Yoruba": "yoruba",
            "Hausa (Nigeria)": "hausa"
        }
    ],
    "Braille": [
        {
            "None": "",
            "Braille (left-handed)": "left_hand",
            "Braille (left-handed inverted thumb)": "left_hand_invert",
            "Braille (right-handed)": "right_hand",
            "Braille (right-handed inverted thumb)": "right_hand_invert"
        }
    ],
    "Turkmen": [
        {
            "None": "",
            "Turkmen (Alt-Q)": "alt"
        }
    ],
    "Mali": [
        {
            "None": "",
            "French (Mali, alt.)": "fr-oss",
            "English (Mali, US, Macintosh)": "us-mac",
            "English (Mali, US, intl.)": "us-intl"
        }
    ],
    "Kikuyu": [
        {
            "None": "",
            "Kikuyu": "kik"
        }
    ],
    "Filipino": [
        {
            "None": "",
            "Filipino (QWERTY, Baybayin)": "qwerty-bay",
            "Filipino (Capewell-Dvorak, Latin)": "capewell-dvorak",
            "Filipino (Capewell-Dvorak, Baybayin)": "capewell-dvorak-bay",
            "Filipino (Capewell-QWERF 2006, Latin)": "capewell-qwerf2k6",
            "Filipino (Capewell-QWERF 2006, Baybayin)": "capewell-qwerf2k6-bay",
            "Filipino (Colemak, Latin)": "colemak",
            "Filipino (Colemak, Baybayin)": "colemak-bay",
            "Filipino (Dvorak, Latin)": "dvorak",
            "Filipino (Dvorak, Baybayin)": "dvorak-bay"
        }
    ],
    "Moldavian": [
        {
            "None": "",
            "Moldavian (Gagauz)": "gag"
        }
    ],
    "Indonesian (Latin)": [
        {
            "None": "",
            "Indonesian (Arab Pegon, phonetic)": "phonetic",
            "Indonesian (Arab Pegon, extended phonetic)": "phoneticx"
        }
    ],
    "Malay (Jawi, Arabic Keyboard)": [
        {
            "None": "",
            "Malay (Jawi, phonetic)": "phonetic"
        }
    ]
}